README.rst
setup.py
beaker_mongodb/__init__.py
beaker_mongodb.egg-info/PKG-INFO
beaker_mongodb.egg-info/SOURCES.txt
beaker_mongodb.egg-info/dependency_links.txt
beaker_mongodb.egg-info/entry_points.txt
beaker_mongodb.egg-info/requires.txt
beaker_mongodb.egg-info/top_level.txt
beaker_mongodb.egg-info/zip-safe
tests/__init__.py
tests/test_default.py
tests/test_nopickle.py
tests/test_sparse.py