Metadata-Version: 1.1
Name: beaker-mongodb
Version: 0.3
Summary: Beaker backend to write sessions and caches to a MongoDB schemaless database.
Home-page: https://github.com/BlueDragonX/beaker_mongodb/
Author: Ryan Bourgeois
Author-email: bluedragonx@gmail.com
License: New BSD License
Keywords: mongo mongodb beaker cache session
Platform: UNKNOWN
Classifier: Development Status :: 4 - Beta
Classifier: Environment :: Other Environment
Classifier: Environment :: Web Environment
Classifier: Intended Audience :: Developers
Classifier: License :: OSI Approved :: BSD License
Classifier: Operating System :: OS Independent
Classifier: Programming Language :: Python
Classifier: Topic :: Database
Classifier: Topic :: Utilities
Classifier: Topic :: Software Development :: Libraries :: Python Modules
Requires: pymongo
Requires: beaker
